LICENSE
MANIFEST.in
README.rst
setup.py
red/__init__.py
red/cli.py
red.egg-info/PKG-INFO
red.egg-info/SOURCES.txt
red.egg-info/dependency_links.txt
red.egg-info/entry_points.txt
red.egg-info/top_level.txt