Metadata-Version: 1.1
Name: red
Version: 0.2.0
Summary: Python regex command-line tool, to replace functionality akin to 'perl -ne'.
Home-page: https://www.bitbucket.org/johannestaas/red
Author: Johan Nestaas
Author-email: johannestaas@gmail.com
License: GPLv3+
Platform: UNKNOWN
Classifier: Development Status :: 3 - Alpha
Classifier: License :: OSI Approved :: GNU General Public License v3 or later (GPLv3+)
Classifier: Environment :: Console
Classifier: Environment :: X11 Applications :: Qt
Classifier: Environment :: MacOS X
Classifier: Environment :: Win32 (MS Windows)
Classifier: Operating System :: POSIX
Classifier: Operating System :: MacOS :: MacOS X
Classifier: Operating System :: Microsoft :: Windows
Classifier: Programming Language :: Python
